README.md
setup.cfg
setup.py
TOPSIS_Atinderpal_101803176/TOPSIS.py
TOPSIS_Atinderpal_101803176.egg-info/PKG-INFO
TOPSIS_Atinderpal_101803176.egg-info/SOURCES.txt
TOPSIS_Atinderpal_101803176.egg-info/dependency_links.txt
TOPSIS_Atinderpal_101803176.egg-info/entry_points.txt
TOPSIS_Atinderpal_101803176.egg-info/requires.txt
TOPSIS_Atinderpal_101803176.egg-info/top_level.txt