Metadata-Version: 2.1
Name: TOPSIS-Atinderpal-101803176
Version: 1.1.0
Summary: A Python package for topsis analysis.
Home-page: UNKNOWN
Author: Atinderpal Kaur
Author-email: kaur.atinder01@gmail.com
License: MIT
Platform: UNKNOWN
Classifier: License :: OSI Approved :: MIT License
Classifier: Programming Language :: Python :: 3.7
